UnitCvrt/UnitConv.py
UnitCvrt/__init__.py
unitcvrt-0.1.7.dist-info/METADATA
unitcvrt-0.1.7.dist-info/WHEEL
unitcvrt-0.1.7.dist-info/top_level.txt
unitcvrt-0.1.7.dist-info/RECORD
